overpassify/__init__.py
overpassify/model.py
overpassify/overpassify.py
overpassify/transform.py
overpassify-1.2.3.dist-info/LICENSE
overpassify-1.2.3.dist-info/METADATA
overpassify-1.2.3.dist-info/WHEEL
overpassify-1.2.3.dist-info/top_level.txt
overpassify-1.2.3.dist-info/RECORD
