Metadata-Version: 2.1
Name: overpassify
Version: 1.2.3
Summary: A tool to more easily develop queries of OpenStreetMap
Home-page: https://github.com/LivInTheLookingGlass/overpassify
Author: Olivia Appleton
Author-email: olivia.kay.appleton@gmail.com
License: LGPLv3
Keywords: OSM OpenStreetMap Overpass OverpassQL Transpiler Transpile
Platform: UNKNOWN
Classifier: Development Status :: 4 - Beta
Classifier: Intended Audience :: Developers
Classifier: License :: OSI Approved :: GNU Lesser General Public License v3 (LGPLv3)
Classifier: Operating System :: OS Independent
Classifier: Topic :: Internet
Classifier: Topic :: Scientific/Engineering :: GIS
Classifier: Topic :: Software Development :: Compilers
Classifier: Programming Language :: Other
Classifier: Programming Language :: Python
Classifier: Programming Language :: Python :: 2
Classifier: Programming Language :: Python :: 3
Classifier: Programming Language :: Python :: 2.7
Classifier: Programming Language :: Python :: 3.3
Classifier: Programming Language :: Python :: 3.4
Classifier: Programming Language :: Python :: 3.5
Classifier: Programming Language :: Python :: 3.6
Classifier: Programming Language :: Python :: 3.7
License-File: LICENSE
Requires-Dist: dill
Requires-Dist: singledispatch
